[
  {
    "name": "Spółdzielnia Socjalna \"Poza Horyzont\"",
    "address": "dolnośląskie 56-300 Milicz, ul. Kolejowa 10",
    "description": "opis: Lp.: 371<br>Województwo: dolnośląskie<br>Adres: 56-300 Milicz, ul. Kolejowa 10<br>Forma prawna: spółdzielnia socjalna<br>NIP: 9161405729<br>REGON: 525364448<br>KRS: 1037480<br>Nazwa i numer innej ewidencji lub rejestru: <br>Data uzyskania statusu: 8/6/2024<br>Cel działalności: działalność reintegracyjna<br>Przedmiot dominującej działalności: DZIAŁALNOŚĆ ZWIĄZANA Z ZAKWATEROWANIEM I USŁUGAMI GASTRONOMICZNYMI<br>adres: dolnośląskie 56-300 Milicz, ul. Kolejowa 10<br>Lp.: 371.0<br>Województwo: dolnośląskie<br>Adres: 56-300 Milicz, ul. Kolejowa 10<br>Forma prawna: spółdzielnia socjalna<br>NIP: 9.161405729E9<br>REGON: 5.25364448E8<br>KRS: 1037480.0<br>Nazwa i numer innej ewidencji lub rejestru: <br>Data uzyskania statusu: 8/6/2024<br>Cel działalności: działalność reintegracyjna<br>Przedmiot dominującej działalności: DZIAŁALNOŚĆ ZWIĄZANA Z ZAKWATEROWANIEM I USŁUGAMI GASTRONOMICZNYMI",
    "styleUrl": "#icon-1899-DB4436",
    "opis": "Lp.: 371\nWojewództwo: dolnośląskie\nAdres: 56-300 Milicz, ul. Kolejowa 10\nForma prawna: spółdzielnia socjalna\nNIP: 9161405729\nREGON: 525364448\nKRS: 1037480\nNazwa i numer innej ewidencji lub rejestru: \nData uzyskania statusu: 8/6/2024\nCel działalności: działalność reintegracyjna\nPrzedmiot dominującej działalności: DZIAŁALNOŚĆ ZWIĄZANA Z ZAKWATEROWANIEM I USŁUGAMI GASTRONOMICZNYMI",
    "adres": "dolnośląskie 56-300 Milicz, ul. Kolejowa 10",
    "Lp.": "371.0",
    "Województwo": "dolnośląskie",
    "Adres": "56-300 Milicz, ul. Kolejowa 10",
    "Forma prawna": "spółdzielnia socjalna",
    "NIP": "9.161405729E9",
    "REGON": "5.25364448E8",
    "KRS": "1037480.0",
    "Nazwa i numer innej ewidencji lub rejestru": null,
    "Data uzyskania statusu": "8/6/2024",
    "Cel działalności": "działalność reintegracyjna",
    "Przedmiot dominującej działalności": "DZIAŁALNOŚĆ ZWIĄZANA Z ZAKWATEROWANIEM I USŁUGAMI GASTRONOMICZNYMI"
  }
]