[
  {
    "name": "Budowa kanalizacji sanitarnej na os. Henin w Poniatowej (ETAP I)",
    "description": "Nr referencyjny umowy: ZT24-06263<br>Data zawarcia umowy pożyczki: 12/20/2024<br>Kwota pożyczki:   249,230.1 <br>Nazwa pożyczkobiorcy: GMINA PONIATOWA<br>Lokalizacja: 51.20052686043496, 22.071038851396196<br>1 Lokalizacja/Miasto Inwestycji: Poniatowa<br>Opis projektu: Budowa kanalizacji sanitarnej na os. Henin w Poniatowej (etap 1)",
    "styleUrl": "#icon-1886-7CB342",
    "Nr referencyjny umowy": "ZT24-06263",
    "Data zawarcia umowy pożyczki": "12/20/2024",
    "Kwota pożyczki": "  249,230.1 ",
    "Nazwa pożyczkobiorcy": "GMINA PONIATOWA",
    "Lokalizacja": "51.20052686043496, 22.071038851396196",
    "1 Lokalizacja/Miasto Inwestycji": "Poniatowa",
    "Opis projektu": "Budowa kanalizacji sanitarnej na os. Henin w Poniatowej (etap 1)"
  }
]