[
  {
    "name": "Rozszerzenie działalności firmy La TurystyQa w województwie zachodniopomorskim.",
    "address": "ZACHODNIOPOMORSKIE Parnowo 2 76-039",
    "description": "Nazwa: ANITA SOKALSKA La TurystyQa<br>Miejsce Realizacji Województwo: ZACHODNIOPOMORSKIE<br>Grantobiorca Miejscowość: Parnowo<br>Grantobiorca Ulica: <br>Grantobiorca Nr budynku: 2<br>Grantobiorca Kod pocztowy: 76-039<br>Wartość wsparcia: 540000",
    "styleUrl": "#icon-1899-0288D1",
    "Nazwa": "ANITA SOKALSKA La TurystyQa",
    "Miejsce Realizacji Województwo": "ZACHODNIOPOMORSKIE",
    "Grantobiorca Miejscowość": "Parnowo",
    "Grantobiorca Ulica": null,
    "Grantobiorca Nr budynku": "2",
    "Grantobiorca Kod pocztowy": "76-039",
    "Wartość wsparcia": 540000.0
  }
]