[
  {
    "name": "Rozwój mini-kawiarni Quick Coffee oraz bistro Świetlica Uniwersytetu Jagiellońskiego w Krakowie w woj. małopolskim (region 3) poprzez wdrożenie nowych produktów i usług oraz transformację cyfrową w przedsiębiorstwie.",
    "address": "Małopolskie Augustynów 51A 97-400",
    "description": "Nazwa: Tomasz Szmaj Quick Coffee<br>Miejsce Realizacji Województwo: Małopolskie<br>Grantobiorca Miejscowość: Augustynów<br>Grantobiorca Ulica: <br>Grantobiorca Nr budynku: 51A<br>Grantobiorca Kod pocztowy: 97-400<br>Wartość wsparcia: 539999.99",
    "styleUrl": "#icon-1899-0288D1",
    "Nazwa": "Tomasz Szmaj Quick Coffee",
    "Miejsce Realizacji Województwo": "Małopolskie",
    "Grantobiorca Miejscowość": "Augustynów",
    "Grantobiorca Ulica": null,
    "Grantobiorca Nr budynku": "51A",
    "Grantobiorca Kod pocztowy": "97-400",
    "Wartość wsparcia": 539999.99
  }
]