[
  {
    "name": "Termomodernizacja Zespołu Szkół Chemicznych przy ul. Łukasiewicza 3 w Bydgoszczy",
    "address": "Jezuicka 85-102 Bydgoszcz KUJAWSKO-POMORSKIE 5,672,156.00 zł",
    "description": "Nazwa podmiotu: Miasto Bydgoszcz<br>Ulica: Jezuicka<br>Nr budynku: 1<br>Kod pocztowy: 85-102<br>Miejscowość: Bydgoszcz<br>Województwo: KUJAWSKO-POMORSKIE<br>Dofinansowanie: 5,672,156.00 zł",
    "styleUrl": "#icon-1726-9C27B0",
    "Nazwa podmiotu": "Miasto Bydgoszcz",
    "Ulica": "Jezuicka",
    "Nr budynku": "1",
    "Kod pocztowy": "85-102",
    "Miejscowość": "Bydgoszcz",
    "Województwo": "KUJAWSKO-POMORSKIE",
    "Dofinansowanie": "5,672,156.00 zł"
  }
]