[
  {
    "name": "Wprowadzenie nowej usługi i wzmocnienie na sytuacje kryzysowe firmy Oriental SPA dzięki zakupowi łodzi rekreacyjnej typu HouseBoat - Region 1",
    "address": "POMORSKIE Gdynia Stanisława Wyspiańskiego 7 81-435",
    "description": "Nazwa: ORIENTAL SPA SPÓŁKA Z OGRANICZONĄ ODPOWIEDZIALNOŚCIĄ<br>Miejsce Realizacji Województwo: POMORSKIE<br>Grantobiorca Miejscowość: Gdynia<br>Grantobiorca Ulica: Stanisława Wyspiańskiego<br>Grantobiorca Nr budynku: 7<br>Grantobiorca Kod pocztowy: 81-435<br>Wartość wsparcia: 540000",
    "styleUrl": "#icon-1899-0288D1",
    "Nazwa": "ORIENTAL SPA SPÓŁKA Z OGRANICZONĄ ODPOWIEDZIALNOŚCIĄ",
    "Miejsce Realizacji Województwo": "POMORSKIE",
    "Grantobiorca Miejscowość": "Gdynia",
    "Grantobiorca Ulica": "Stanisława Wyspiańskiego",
    "Grantobiorca Nr budynku": "7",
    "Grantobiorca Kod pocztowy": "81-435",
    "Wartość wsparcia": 540000.0
  }
]