[
  {
    "name": "Zwiększenie odporności przedsiębiorstwa K2 HOTEL SPÓŁKA Z OGRANICZONĄ ODPOWIEDZIALNOŚCIĄ SPÓŁKA KOMANDYTOWA na sytuacje kryzysowe w wyniku dywersyfikacji prowadzonej działalności (REGION 5: województwo dolnośląskie).",
    "address": "DOLNOŚLĄSKIE Wrocław 10 50-071",
    "description": "Nazwa: K2 HOTEL SPÓŁKA Z OGRANICZONĄ ODPOWIEDZIALNOŚCIĄ SPÓŁKA KOMANDYTOWA<br>Miejsce Realizacji Województwo: DOLNOŚLĄSKIE<br>Grantobiorca Miejscowość: Wrocław<br>Grantobiorca Ulica: <br>Grantobiorca Nr budynku: 10<br>Grantobiorca Kod pocztowy: 50-071<br>Wartość wsparcia: 488799.88",
    "styleUrl": "#icon-1899-0288D1",
    "Nazwa": "K2 HOTEL SPÓŁKA Z OGRANICZONĄ ODPOWIEDZIALNOŚCIĄ SPÓŁKA KOMANDYTOWA",
    "Miejsce Realizacji Województwo": "DOLNOŚLĄSKIE",
    "Grantobiorca Miejscowość": "Wrocław",
    "Grantobiorca Ulica": null,
    "Grantobiorca Nr budynku": "10",
    "Grantobiorca Kod pocztowy": "50-071",
    "Wartość wsparcia": 488799.88
  }
]