[
  {
    "name": "Rozszerzenie i dywersyfikacja działalności Runforest działającej w województwie lubuskim, w Regionie 5",
    "address": "LUBUSKIE Niedźwiedź 7 66-220",
    "description": "Nazwa: RUNFOREST SAWICKI KARATAJ SPÓŁKA JAWNA<br>Miejsce Realizacji Województwo: LUBUSKIE<br>Grantobiorca Miejscowość: Niedźwiedź<br>Grantobiorca Ulica: <br>Grantobiorca Nr budynku: 7<br>Grantobiorca Kod pocztowy: 66-220<br>Wartość wsparcia: 346759.75",
    "styleUrl": "#icon-1899-0288D1",
    "Nazwa": "RUNFOREST SAWICKI KARATAJ SPÓŁKA JAWNA",
    "Miejsce Realizacji Województwo": "LUBUSKIE",
    "Grantobiorca Miejscowość": "Niedźwiedź",
    "Grantobiorca Ulica": null,
    "Grantobiorca Nr budynku": "7",
    "Grantobiorca Kod pocztowy": "66-220",
    "Wartość wsparcia": 346759.75
  }
]