[
  {
    "name": "Rozwój infrastruktury zintegrowanej z transportem zbiorowym",
    "description": "Nr referencyjny umowy: ZT24-05992<br>Data zawarcia umowy pożyczki: 12/12/2024<br>Kwota pożyczki:   135,056.8 <br>Nazwa pożyczkobiorcy: GMINA WROCŁAW<br>Lokalizacja: 51.12620144986447, 17.03703441925135<br>1 Lokalizacja/Miasto Inwestycji: Wrocław<br>Opis projektu: Przedmiotem projektu była budowa infrastruktury skierowanej na zintegrowanie jej z transportem zbiorowym, w tym budowa chodnika, przejścia dla pieszych i przystanku autobusowego wraz z jego doświetleniem.<br>Realizacja Projektu przyczynia się do poprawy bezpieczeństwa niechronionych użytkowników drogi, ze szczególnym uwzględnieniem pieszych (priorytetyzacja mobilności pieszej) oraz do zwiększenia dostępności przyjaznych środowisku usług publicznych (w tym do komunikacji zbiorowej). Realizacja Projektu to również umożliwienie mieszkańcom Wrocławia zmiany zachowań transportowych – zastąpienie samochodów spalinowych komunikacją zbiorową, a tym samym docelowo zmniejszenie ilości spalin i poprawa jakości powietrza.",
    "styleUrl": "#icon-1886-7CB342",
    "Nr referencyjny umowy": "ZT24-05992",
    "Data zawarcia umowy pożyczki": "12/12/2024",
    "Kwota pożyczki": "  135,056.8 ",
    "Nazwa pożyczkobiorcy": "GMINA WROCŁAW",
    "Lokalizacja": "51.12620144986447, 17.03703441925135",
    "1 Lokalizacja/Miasto Inwestycji": "Wrocław",
    "Opis projektu": "Przedmiotem projektu była budowa infrastruktury skierowanej na zintegrowanie jej z transportem zbiorowym, w tym budowa chodnika, przejścia dla pieszych i przystanku autobusowego wraz z jego doświetleniem.\nRealizacja Projektu przyczynia się do poprawy bezpieczeństwa niechronionych użytkowników drogi, ze szczególnym uwzględnieniem pieszych (priorytetyzacja mobilności pieszej) oraz do zwiększenia dostępności przyjaznych środowisku usług publicznych (w tym do komunikacji zbiorowej). Realizacja Projektu to również umożliwienie mieszkańcom Wrocławia zmiany zachowań transportowych – zastąpienie samochodów spalinowych komunikacją zbiorową, a tym samym docelowo zmniejszenie ilości spalin i poprawa jakości powietrza."
  }
]