[
  {
    "name": "Ogrodnictwo",
    "address": "lubelskie  Opole Lubelskie, Kluczkowice-Osiedle 2",
    "description": "Województwo: lubelskie <br>Adres: Opole Lubelskie, Kluczkowice-Osiedle 2<br>OOW: Powiat Opolski<br>Dofinansowanie:   9,589,870.67 zł <br>Strona www: <br>Uruchomienie: do 30.06.2025",
    "styleUrl": "#icon-1582-673AB7",
    "Województwo": "lubelskie ",
    "Adres": "Opole Lubelskie, Kluczkowice-Osiedle 2",
    "OOW": "Powiat Opolski",
    "Dofinansowanie": "  9,589,870.67 zł ",
    "Strona www": null,
    "Uruchomienie": "do 30.06.2025"
  }
]