{
    "name": "Skwer Miasta Światła",
    "description": "Nr referencyjny umowy: ZT24-04163<br>Data zawarcia umowy pożyczki: 10/17/2024<br>Kwota pożyczki:   84,238.6 <br>Nazwa pożyczkobiorcy: MIASTO GORLICE<br>Lokalizacja: 49.66109943344715, 21.1593032491465<br>1 Lokalizacja/Miasto Inwestycji: Gorlice<br>Opis projektu: Wyodrębnienie strefy odpoczynku, nasadzenie nowej roślinności z upamiętniającym napisem LED miało na celu stworzenie funkcjonalnej i estetycznej przestrzeni rekreacyjnej. Ponadto edukację historyczną, co jest kluczowe dla budowania wspólnoty i atrakcyjności miejsca do życia oraz promocji turystyki.",
    "styleUrl": "#icon-1886-7CB342",
    "Nr referencyjny umowy": "ZT24-04163",
    "Data zawarcia umowy pożyczki": "10/17/2024",
    "Kwota pożyczki": "  84,238.6 ",
    "Nazwa pożyczkobiorcy": "MIASTO GORLICE",
    "Lokalizacja": "49.66109943344715, 21.1593032491465",
    "1 Lokalizacja/Miasto Inwestycji": "Gorlice",
    "Opis projektu": "Wyodrębnienie strefy odpoczynku, nasadzenie nowej roślinności z upamiętniającym napisem LED miało na celu stworzenie funkcjonalnej i estetycznej przestrzeni rekreacyjnej. Ponadto edukację historyczną, co jest kluczowe dla budowania wspólnoty i atrakcyjności miejsca do życia oraz promocji turystyki."
}