{
    "name": "Budowa kanalizacji sanitarnej w ulicy Czajki w Łowiczu",
    "description": "Nr referencyjny umowy: ZT24-04188<br>Data zawarcia umowy pożyczki: 10/23/2024<br>Kwota pożyczki:   2,123,230.1 <br>Nazwa pożyczkobiorcy: MIASTO ŁOWICZ<br>Lokalizacja: 52.090433256037706, 19.939052808260676<br>1 Lokalizacja/Miasto Inwestycji: Łowicz<br>Opis projektu: Budowa kanalizacji sanitarnej w ulicy Czajki w Łowiczu",
    "styleUrl": "#icon-1886-7CB342",
    "Nr referencyjny umowy": "ZT24-04188",
    "Data zawarcia umowy pożyczki": "10/23/2024",
    "Kwota pożyczki": "  2,123,230.1 ",
    "Nazwa pożyczkobiorcy": "MIASTO ŁOWICZ",
    "Lokalizacja": "52.090433256037706, 19.939052808260676",
    "1 Lokalizacja/Miasto Inwestycji": "Łowicz",
    "Opis projektu": "Budowa kanalizacji sanitarnej w ulicy Czajki w Łowiczu"
}