{
    "name": "Termomodernizacja budynku edukacyjnego na terenie gminy Oleśnica",
    "address": "Nadstawie 28-220 Oleśnica ŚWIĘTOKRZYSKIE 447,029.19 zł",
    "description": "Nazwa podmiotu: Gmina Oleśnica<br>Ulica: Nadstawie<br>Nr budynku: 1<br>Kod pocztowy: 28-220<br>Miejscowość: Oleśnica<br>Województwo: ŚWIĘTOKRZYSKIE<br>Dofinansowanie: 447,029.19 zł",
    "styleUrl": "#icon-1726-9C27B0",
    "Nazwa podmiotu": "Gmina Oleśnica",
    "Ulica": "Nadstawie",
    "Nr budynku": "1",
    "Kod pocztowy": "28-220",
    "Miejscowość": "Oleśnica",
    "Województwo": "ŚWIĘTOKRZYSKIE",
    "Dofinansowanie": "447,029.19 zł"
}