{
    "name": "Eventy i festyny dla firm.",
    "address": "Śląskie Mikołów Zgody 5a 43-190",
    "description": "Nazwa: Damian Herdzina firma Gx-Gastro<br>Miejsce Realizacji Województwo: Śląskie<br>Grantobiorca Miejscowość: Mikołów<br>Grantobiorca Ulica: Zgody<br>Grantobiorca Nr budynku: 5a<br>Grantobiorca Kod pocztowy: 43-190<br>Wartość wsparcia: 68212.99",
    "styleUrl": "#icon-1899-0288D1",
    "Nazwa": "Damian Herdzina firma Gx-Gastro",
    "Miejsce Realizacji Województwo": "Śląskie",
    "Grantobiorca Miejscowość": "Mikołów",
    "Grantobiorca Ulica": "Zgody",
    "Grantobiorca Nr budynku": "5a",
    "Grantobiorca Kod pocztowy": "43-190",
    "Wartość wsparcia": 68212.99
}