{
    "name": "Dywersyfikacja działalności związanej z wystawianiem przedstawień artystycznych poprzez utworzenie Klubu Filmowego w regionie 4 (opolskie)",
    "address": "OPOLSKIE Prudnik Klasztorna 16 48-200",
    "description": "Nazwa: FB Studio Krystian Nowak<br>Miejsce Realizacji Województwo: OPOLSKIE<br>Grantobiorca Miejscowość: Prudnik<br>Grantobiorca Ulica: Klasztorna<br>Grantobiorca Nr budynku: 16<br>Grantobiorca Kod pocztowy: 48-200<br>Wartość wsparcia: 144780.75",
    "styleUrl": "#icon-1899-0288D1",
    "Nazwa": "FB Studio Krystian Nowak",
    "Miejsce Realizacji Województwo": "OPOLSKIE",
    "Grantobiorca Miejscowość": "Prudnik",
    "Grantobiorca Ulica": "Klasztorna",
    "Grantobiorca Nr budynku": "16",
    "Grantobiorca Kod pocztowy": "48-200",
    "Wartość wsparcia": 144780.75
}