{
    "name": "Wdrożenie programu wzmocnienia i uodpornienia działalności na sytuacje kryzysowe Firmy FUN SPORT Kowalczyk Robert",
    "address": "DOLNOŚLĄSKIE Bolesławiec Jana Pawła II 34 59-700",
    "description": "Nazwa: KOWALCZYK ROBERT FUN-SPORT<br>Miejsce Realizacji Województwo: DOLNOŚLĄSKIE<br>Grantobiorca Miejscowość: Bolesławiec<br>Grantobiorca Ulica: Jana Pawła II<br>Grantobiorca Nr budynku: 34<br>Grantobiorca Kod pocztowy: 59-700<br>Wartość wsparcia: 478888.93",
    "styleUrl": "#icon-1899-0288D1",
    "Nazwa": "KOWALCZYK ROBERT FUN-SPORT",
    "Miejsce Realizacji Województwo": "DOLNOŚLĄSKIE",
    "Grantobiorca Miejscowość": "Bolesławiec",
    "Grantobiorca Ulica": "Jana Pawła II",
    "Grantobiorca Nr budynku": "34",
    "Grantobiorca Kod pocztowy": "59-700",
    "Wartość wsparcia": 478888.93
}