{
    "name": "Stworzenie cukierni z lodziarnią, uruchomienie wypożyczalni rowerów oraz autonomiczny system meldunkowy jako dywersyfikacja działalności ośrodka wypoczynkowo - rehabilitacyjnego Jantar w Niechorzu.",
    "address": "ZACHODNIOPOMORSKIE Niechorze Aleja Bursztynowa 31 72-350",
    "description": "Nazwa: Henryk Gmyrek<br>Miejsce Realizacji Województwo: ZACHODNIOPOMORSKIE<br>Grantobiorca Miejscowość: Niechorze<br>Grantobiorca Ulica: Aleja Bursztynowa<br>Grantobiorca Nr budynku: 31<br>Grantobiorca Kod pocztowy: 72-350<br>Wartość wsparcia: 333711",
    "styleUrl": "#icon-1899-0288D1",
    "Nazwa": "Henryk Gmyrek",
    "Miejsce Realizacji Województwo": "ZACHODNIOPOMORSKIE",
    "Grantobiorca Miejscowość": "Niechorze",
    "Grantobiorca Ulica": "Aleja Bursztynowa",
    "Grantobiorca Nr budynku": "31",
    "Grantobiorca Kod pocztowy": "72-350",
    "Wartość wsparcia": 333711.0
}