{
    "name": "Gminny Żłobek w Zembrzyce",
    "address": "Małopolskie Suski Zembrzyce 34-210 Zembrzyce 261",
    "description": "opis: Województwo: Małopolskie<br>Powiat: Suski<br>Miejscowość: Zembrzyce<br>Kod pocztowy: 34-210<br>Ulica: Zembrzyce<br>Numer: 261<br>adres: Małopolskie Suski Zembrzyce 34-210 Zembrzyce 261<br>Województwo: Małopolskie<br>Powiat: Suski<br>Miejscowość: Zembrzyce<br>Kod pocztowy: 34-210<br>Ulica: Zembrzyce<br>Numer: 261",
    "styleUrl": "#icon-1899-DB4436",
    "opis": "Województwo: Małopolskie\nPowiat: Suski\nMiejscowość: Zembrzyce\nKod pocztowy: 34-210\nUlica: Zembrzyce\nNumer: 261",
    "adres": "Małopolskie Suski Zembrzyce 34-210 Zembrzyce 261",
    "Województwo": "Małopolskie",
    "Powiat": "Suski",
    "Miejscowość": "Zembrzyce",
    "Kod pocztowy": "34-210",
    "Ulica": "Zembrzyce",
    "Numer": "261"
}