{
    "name": "Miejski Żłobek w Czarnym Dunajcu",
    "address": "Małopolskie Nowotarski Czarny Dunajec 34-470 Targowa 1C",
    "description": "opis: Województwo: Małopolskie<br>Powiat: Nowotarski<br>Miejscowość: Czarny Dunajec<br>Kod pocztowy: 34-470<br>Ulica: Targowa<br>Numer: 1C<br>adres: Małopolskie Nowotarski Czarny Dunajec 34-470 Targowa 1C<br>Województwo: Małopolskie<br>Powiat: Nowotarski<br>Miejscowość: Czarny Dunajec<br>Kod pocztowy: 34-470<br>Ulica: Targowa<br>Numer: 1C",
    "styleUrl": "#icon-1899-DB4436",
    "opis": "Województwo: Małopolskie\nPowiat: Nowotarski\nMiejscowość: Czarny Dunajec\nKod pocztowy: 34-470\nUlica: Targowa\nNumer: 1C",
    "adres": "Małopolskie Nowotarski Czarny Dunajec 34-470 Targowa 1C",
    "Województwo": "Małopolskie",
    "Powiat": "Nowotarski",
    "Miejscowość": "Czarny Dunajec",
    "Kod pocztowy": "34-470",
    "Ulica": "Targowa",
    "Numer": "1C"
}