{
    "name": "Wzrost odporności przedsiębiorstwa na sytuacje kryzysowe poprzez dywersyfikację prowadzonej działalności dzięki wprowadzeniu nowych usług – utworzenie Strefy Relaxu oraz unowocześnienie wypożyczalni sprzętu rekreacyjnego-sportowego w województwie małopolskim (region 3).",
    "address": "MAŁOPOLSKIE Łososina Dolna 412 33-314",
    "description": "Nazwa: EURO-CARS Krzysztof Furtak<br>Miejsce Realizacji Województwo: MAŁOPOLSKIE<br>Grantobiorca Miejscowość: Łososina Dolna<br>Grantobiorca Ulica: <br>Grantobiorca Nr budynku: 412<br>Grantobiorca Kod pocztowy: 33-314<br>Wartość wsparcia: 539964.22",
    "styleUrl": "#icon-1899-0288D1",
    "Nazwa": "EURO-CARS Krzysztof Furtak",
    "Miejsce Realizacji Województwo": "MAŁOPOLSKIE",
    "Grantobiorca Miejscowość": "Łososina Dolna",
    "Grantobiorca Ulica": null,
    "Grantobiorca Nr budynku": "412",
    "Grantobiorca Kod pocztowy": "33-314",
    "Wartość wsparcia": 539964.22
}