{
    "name": "Dywersyfikacja przedsiębiorstwa Ryszard Iwaszkiewicz AUTO- MARKET w regionie nr 2",
    "address": "PODLASKIE Białystok Ukośna 22E 15-836",
    "description": "Nazwa: Ryszard Iwaszkiewicz AUTO - MARKET<br>Miejsce Realizacji Województwo: PODLASKIE<br>Grantobiorca Miejscowość: Białystok<br>Grantobiorca Ulica: Ukośna<br>Grantobiorca Nr budynku: 22E<br>Grantobiorca Kod pocztowy: 15-836<br>Wartość wsparcia: 514088.1",
    "styleUrl": "#icon-1899-0288D1",
    "Nazwa": "Ryszard Iwaszkiewicz AUTO - MARKET",
    "Miejsce Realizacji Województwo": "PODLASKIE",
    "Grantobiorca Miejscowość": "Białystok",
    "Grantobiorca Ulica": "Ukośna",
    "Grantobiorca Nr budynku": "22E",
    "Grantobiorca Kod pocztowy": "15-836",
    "Wartość wsparcia": 514088.1
}