{
    "name": "Dywersyfikacja działalności firmy \"Wilga Catering\" w celu zwiększenia odporności na sytuacje kryzysowe w województwie mazowieckim poprzez wprowadzenie nowej usługi diety pudełkowej z dowozem",
    "address": "MAZOWIECKIE Rusiec Bursztynowa 19 05-830",
    "description": "Nazwa: PIOTR WILGA \"Wilga Catering\"<br>Miejsce Realizacji Województwo: MAZOWIECKIE<br>Grantobiorca Miejscowość: Rusiec<br>Grantobiorca Ulica: Bursztynowa<br>Grantobiorca Nr budynku: 19<br>Grantobiorca Kod pocztowy: 05-830<br>Wartość wsparcia: 420187.5",
    "styleUrl": "#icon-1899-0288D1",
    "Nazwa": "PIOTR WILGA \"Wilga Catering\"",
    "Miejsce Realizacji Województwo": "MAZOWIECKIE",
    "Grantobiorca Miejscowość": "Rusiec",
    "Grantobiorca Ulica": "Bursztynowa",
    "Grantobiorca Nr budynku": "19",
    "Grantobiorca Kod pocztowy": "05-830",
    "Wartość wsparcia": 420187.5
}