{
    "name": "Fundacja Creative",
    "address": "podkarpackie 35-304 Rzeszów, al. gen. Władysława Sikorskiego 66",
    "description": "opis: Lp.: 163<br>Województwo: podkarpackie<br>Adres: 35-304 Rzeszów, al. gen. Władysława Sikorskiego 66<br>Forma prawna: organizacja pozarządowa<br>NIP: 5170423110<br>REGON: 521203518<br>KRS: 953325<br>Nazwa i numer innej ewidencji lub rejestru: <br>Data uzyskania statusu: 5/22/2025<br>Cel działalności: działalność reintegracyjna<br>Przedmiot dominującej działalności:<br>adres: podkarpackie 35-304 Rzeszów, al. gen. Władysława Sikorskiego 66<br>Lp.: 163.0<br>Województwo: podkarpackie<br>Adres: 35-304 Rzeszów, al. gen. Władysława Sikorskiego 66<br>Forma prawna: organizacja pozarządowa<br>NIP: 5.17042311E9<br>REGON: 5.21203518E8<br>KRS: 953325.0<br>Nazwa i numer innej ewidencji lub rejestru: <br>Data uzyskania statusu: 5/22/2025<br>Cel działalności: działalność reintegracyjna<br>Przedmiot dominującej działalności: ",
    "styleUrl": "#icon-1899-DB4436",
    "opis": "Lp.: 163\nWojewództwo: podkarpackie\nAdres: 35-304 Rzeszów, al. gen. Władysława Sikorskiego 66\nForma prawna: organizacja pozarządowa\nNIP: 5170423110\nREGON: 521203518\nKRS: 953325\nNazwa i numer innej ewidencji lub rejestru: \nData uzyskania statusu: 5/22/2025\nCel działalności: działalność reintegracyjna\nPrzedmiot dominującej działalności:",
    "adres": "podkarpackie 35-304 Rzeszów, al. gen. Władysława Sikorskiego 66",
    "Lp.": "163.0",
    "Województwo": "podkarpackie",
    "Adres": "35-304 Rzeszów, al. gen. Władysława Sikorskiego 66",
    "Forma prawna": "organizacja pozarządowa",
    "NIP": "5.17042311E9",
    "REGON": "5.21203518E8",
    "KRS": "953325.0",
    "Nazwa i numer innej ewidencji lub rejestru": null,
    "Data uzyskania statusu": "5/22/2025",
    "Cel działalności": "działalność reintegracyjna",
    "Przedmiot dominującej działalności": null
}