{
    "name": "Rozbudowa hali magazynowej - Modernizacja hali i doposażenie firmy w niezbędne urządzenia w tym fotowoltaikę do polepszenia efektywności procesu konfekcjonowania warzyw.",
    "address": "Cedrowa 16 83-022 Grabiny-Zameczek",
    "description": "Grantobiorca nazwa: Emilian Wilczewski<br>Wartość grantu: 854,766.45 zł<br>Grantobiorca Ulica: Cedrowa<br>Grantobiorca Nr budynku: 16<br>Grantobiorca Kod pocztowy: 83-022<br>Grantobiorca Miejscowość: Grabiny-Zameczek",
    "styleUrl": "#icon-1566-7CB342",
    "Grantobiorca nazwa": "Emilian Wilczewski",
    "Wartość grantu": "854,766.45 zł",
    "Grantobiorca Ulica": "Cedrowa",
    "Grantobiorca Nr budynku": "16",
    "Grantobiorca Kod pocztowy": "83-022",
    "Grantobiorca Miejscowość": "Grabiny-Zameczek"
}