{
    "name": "USPRAWNIENIE PROCESÓW TECHNOLOGICZNYCH W ZAKŁADZIE SPRZEDAŻY HURTOWEJ JAJ",
    "address": "12 97-403 TERESIN",
    "description": "Grantobiorca nazwa: GRUPA PRODUCENTÓW ROLNYCH SUFLIDOWO SPÓŁKA Z OGRANICZONĄ ODPOWIEDZIALNOŚCIĄ<br>Wartość grantu: 7,444,145.30 zł<br>Grantobiorca Ulica: <br>Grantobiorca Nr budynku: 12<br>Grantobiorca Kod pocztowy: 97-403<br>Grantobiorca Miejscowość: TERESIN",
    "styleUrl": "#icon-1566-7CB342",
    "Grantobiorca nazwa": "GRUPA PRODUCENTÓW ROLNYCH SUFLIDOWO SPÓŁKA Z OGRANICZONĄ ODPOWIEDZIALNOŚCIĄ",
    "Wartość grantu": "7,444,145.30 zł",
    "Grantobiorca Ulica": null,
    "Grantobiorca Nr budynku": "12",
    "Grantobiorca Kod pocztowy": "97-403",
    "Grantobiorca Miejscowość": "TERESIN"
}