{
    "name": "PRZEDSIĘWZIĘCIE MAJĄCE NA CELU USPRAWNIENIA PROCESÓW DLA MASARNI",
    "address": "Ceramiczna 13 34-400 Nowy Targ",
    "description": "Grantobiorca nazwa: Masarnia Tradycyjna Spółka Cywilna Czesław Trzópek Mariusz Trzópek Marta Burkat<br>Wartość grantu: 134,550.00 zł<br>Grantobiorca Ulica: Ceramiczna<br>Grantobiorca Nr budynku: 13<br>Grantobiorca Kod pocztowy: 34-400<br>Grantobiorca Miejscowość: Nowy Targ",
    "styleUrl": "#icon-1566-7CB342",
    "Grantobiorca nazwa": "Masarnia Tradycyjna Spółka Cywilna Czesław Trzópek Mariusz Trzópek Marta Burkat",
    "Wartość grantu": "134,550.00 zł",
    "Grantobiorca Ulica": "Ceramiczna",
    "Grantobiorca Nr budynku": "13",
    "Grantobiorca Kod pocztowy": "34-400",
    "Grantobiorca Miejscowość": "Nowy Targ"
}