{
    "name": "Rozwój przedsiębiorstwa MIODZIARZE p. z o.o.",
    "address": "12 B 09-411 Srebrna",
    "description": "Grantobiorca nazwa: MIODZIARZE Spółka z ograniczoną odpowiedzialnością<br>Wartość grantu: 530,583.47 zł<br>Grantobiorca Ulica: <br>Grantobiorca Nr budynku: 12 B<br>Grantobiorca Kod pocztowy: 09-411<br>Grantobiorca Miejscowość: Srebrna",
    "styleUrl": "#icon-1566-7CB342",
    "Grantobiorca nazwa": "MIODZIARZE Spółka z ograniczoną odpowiedzialnością",
    "Wartość grantu": "530,583.47 zł",
    "Grantobiorca Ulica": null,
    "Grantobiorca Nr budynku": "12 B",
    "Grantobiorca Kod pocztowy": "09-411",
    "Grantobiorca Miejscowość": "Srebrna"
}