{
    "name": "Dywersyfikacja działalności poprzez powstanie kawiarni z asortymentem piekarniczo-cukierniczym. Zakup i instalacja systemu POS oraz uruchomienie stron internetowych. Szkolenie personelu mające na celu podnoszenie umiejętności i kompetencji pracowników. Analiza dotychczasowego modelu biznesowego przedsiębiorstwa pozwalająca na opracowanie nowego modelu biznesowego pod kątem rozszerzenia lub dywersyfikacji działalności. Region 2: woj. mazowieckie, podlaskie, warmińsko-mazurskie.",
    "address": "MAZOWIECKIE Wołomin Nowa Wieś 18 05-200",
    "description": "Nazwa: BEST EVENT CATERING ŁUKASZ BIREK<br>Miejsce Realizacji Województwo: MAZOWIECKIE<br>Grantobiorca Miejscowość: Wołomin<br>Grantobiorca Ulica: Nowa Wieś<br>Grantobiorca Nr budynku: 18<br>Grantobiorca Kod pocztowy: 05-200<br>Wartość wsparcia: 533085.97",
    "styleUrl": "#icon-1899-0288D1",
    "Nazwa": "BEST EVENT CATERING ŁUKASZ BIREK",
    "Miejsce Realizacji Województwo": "MAZOWIECKIE",
    "Grantobiorca Miejscowość": "Wołomin",
    "Grantobiorca Ulica": "Nowa Wieś",
    "Grantobiorca Nr budynku": "18",
    "Grantobiorca Kod pocztowy": "05-200",
    "Wartość wsparcia": 533085.97
}