{
    "name": "Modernizacja i rozbudowa infrastruktury gastronomicznej z wprowadzeniem innowacyjnych usług SPA i rekreacji oraz instalacji fotowoltaicznych w Restauracji Eldorado i Restauracji Pod Borem Warzybok S.C. w regionie 5.",
    "address": "WIELKOPOLSKIE Rzetnia 110 63-600",
    "description": "Nazwa: POD BOREM WARZYBOK S.C. <br>Miejsce Realizacji Województwo: WIELKOPOLSKIE<br>Grantobiorca Miejscowość: Rzetnia<br>Grantobiorca Ulica: <br>Grantobiorca Nr budynku: 110<br>Grantobiorca Kod pocztowy: 63-600<br>Wartość wsparcia: 478247.44",
    "styleUrl": "#icon-1899-0288D1",
    "Nazwa": "POD BOREM WARZYBOK S.C. ",
    "Miejsce Realizacji Województwo": "WIELKOPOLSKIE",
    "Grantobiorca Miejscowość": "Rzetnia",
    "Grantobiorca Ulica": null,
    "Grantobiorca Nr budynku": "110",
    "Grantobiorca Kod pocztowy": "63-600",
    "Wartość wsparcia": 478247.44
}