{
    "name": "Żłobek Samorządowy \"Kraina Malucha\" w Albertowie",
    "address": "Lubelskie Łęczyński Albertów 21-013 Albertów 4",
    "description": "opis: Województwo: Lubelskie<br>Powiat: Łęczyński<br>Miejscowość: Albertów<br>Kod pocztowy: 21-013<br>Ulica: Albertów<br>Numer: 4<br>adres: Lubelskie Łęczyński Albertów 21-013 Albertów 4<br>Województwo: Lubelskie<br>Powiat: Łęczyński<br>Miejscowość: Albertów<br>Kod pocztowy: 21-013<br>Ulica: Albertów<br>Numer: 4",
    "styleUrl": "#icon-1899-DB4436",
    "opis": "Województwo: Lubelskie\nPowiat: Łęczyński\nMiejscowość: Albertów\nKod pocztowy: 21-013\nUlica: Albertów\nNumer: 4",
    "adres": "Lubelskie Łęczyński Albertów 21-013 Albertów 4",
    "Województwo": "Lubelskie",
    "Powiat": "Łęczyński",
    "Miejscowość": "Albertów",
    "Kod pocztowy": "21-013",
    "Ulica": "Albertów",
    "Numer": "4"
}