{
    "name": "Bajkowy ogród",
    "description": "Nr referencyjny umowy: ZT24-06403<br>Data zawarcia umowy pożyczki: 12/27/2024<br>Kwota pożyczki:   84,230.5 <br>Nazwa pożyczkobiorcy: KIELCE MIASTO NA PRAWACH POWIATU<br>Lokalizacja: 50.89629534207127, 20.67154608364234<br>1 Lokalizacja/Miasto Inwestycji: Kielce<br>Opis projektu: Bajkowy ogród. - Zazielenianie terenów miejskich",
    "styleUrl": "#icon-1886-7CB342",
    "Nr referencyjny umowy": "ZT24-06403",
    "Data zawarcia umowy pożyczki": "12/27/2024",
    "Kwota pożyczki": "  84,230.5 ",
    "Nazwa pożyczkobiorcy": "KIELCE MIASTO NA PRAWACH POWIATU",
    "Lokalizacja": "50.89629534207127, 20.67154608364234",
    "1 Lokalizacja/Miasto Inwestycji": "Kielce",
    "Opis projektu": "Bajkowy ogród. - Zazielenianie terenów miejskich"
}