{
    "name": "Budowa chodników przy drogach powiatowych na terenie Powiatu Golubsko-Dobrzyńskiego",
    "description": "Nr referencyjny umowy: ZT24-06475<br>Data zawarcia umowy pożyczki: 3/3/2025<br>Kwota pożyczki:   607,461.1 <br>Nazwa pożyczkobiorcy: POWIAT GOLUBSKO-DOBRZYŃSKI<br>Lokalizacja: 53.11309577594654, 19.016153459477785<br>1 Lokalizacja/Miasto Inwestycji: <br>Opis projektu: Budowa chodników przy drogach powiatowych na terenie Powiatu Golubsko-Dobrzyńskiego.<br>Przed wykonaniem projektu dwie drogi nie były dostosowane do ruchu pieszego. Ruch pieszy odbywał się nieutwardzonym poboczem.<br>Stan po realizacji projektu: Przedmiotem projektu jest wykonanie dwóch chodników na terenie Powiatu Golubsko-Dobrzyńskiego przy drogach powiatowych. Pierwszy wybudowany został przy drodze powiatowej Nr 2121C Ciechocin-Świętosław od km 0+706 do km 1+965 a drugi przy drodze powiatowej nr 2125C Paliwodzizna - Macikowo - Węgiersk od km 1+883 do 2+337. Każdy z chodników wyposażony został w przejście dla pieszych oświetlone lampami hybrydowymi.<br>Dzięki realizacji zadania powstały dwa chodniki przy drogach powiatowych umożliwiające swobodne i bezpieczne poruszanie się pieszych posiadające oświetlone przejścia dla pieszych. Przełoży się to na częstsze wybieranie tego sposobu poruszania się po drogach powiatowych, co wpłynie bezpośrednio na zmniejszenie emisji spalin do atmosfery. Teren nabrał nowej funkcji co przełoży się na lepszy komfort życia i zdrowia mieszkańców, dzięki nowej możliwości spędzania czasu na świeżym powietrzu. Dzięki powstaniu chodników Mieszkańcy zostali zachęceni do nowej atrakcyjnej możliwości spędzania czasu na świeżym powietrzu.",
    "styleUrl": "#icon-1886-7CB342",
    "Nr referencyjny umowy": "ZT24-06475",
    "Data zawarcia umowy pożyczki": "3/3/2025",
    "Kwota pożyczki": "  607,461.1 ",
    "Nazwa pożyczkobiorcy": "POWIAT GOLUBSKO-DOBRZYŃSKI",
    "Lokalizacja": "53.11309577594654, 19.016153459477785",
    "1 Lokalizacja/Miasto Inwestycji": null,
    "Opis projektu": "Budowa chodników przy drogach powiatowych na terenie Powiatu Golubsko-Dobrzyńskiego.\nPrzed wykonaniem projektu dwie drogi nie były dostosowane do ruchu pieszego. Ruch pieszy odbywał się nieutwardzonym poboczem.\nStan po realizacji projektu: Przedmiotem projektu jest wykonanie dwóch chodników na terenie Powiatu Golubsko-Dobrzyńskiego przy drogach powiatowych. Pierwszy wybudowany został przy drodze powiatowej Nr 2121C Ciechocin-Świętosław od km 0+706 do km 1+965 a drugi przy drodze powiatowej nr 2125C Paliwodzizna - Macikowo - Węgiersk od km 1+883 do 2+337. Każdy z chodników wyposażony został w przejście dla pieszych oświetlone lampami hybrydowymi.\nDzięki realizacji zadania powstały dwa chodniki przy drogach powiatowych umożliwiające swobodne i bezpieczne poruszanie się pieszych posiadające oświetlone przejścia dla pieszych. Przełoży się to na częstsze wybieranie tego sposobu poruszania się po drogach powiatowych, co wpłynie bezpośrednio na zmniejszenie emisji spalin do atmosfery. Teren nabrał nowej funkcji co przełoży się na lepszy komfort życia i zdrowia mieszkańców, dzięki nowej możliwości spędzania czasu na świeżym powietrzu. Dzięki powstaniu chodników Mieszkańcy zostali zachęceni do nowej atrakcyjnej możliwości spędzania czasu na świeżym powietrzu."
}