{
    "name": "Dywersyfikacja działalności firmy \"OKI - EVENT\" MACIEJ KUBICKI - region wielkopolskie",
    "address": "WIELKOPOLSKIE Poznań Grunwaldzka 33b 60-783",
    "description": "Nazwa: \"OKI - EVENT\" MACIEJ KUBICKI <br>Miejsce Realizacji Województwo: WIELKOPOLSKIE<br>Grantobiorca Miejscowość: Poznań<br>Grantobiorca Ulica: Grunwaldzka<br>Grantobiorca Nr budynku: 33b<br>Grantobiorca Kod pocztowy: 60-783<br>Wartość wsparcia: 504800.96",
    "styleUrl": "#icon-1899-0288D1",
    "Nazwa": "\"OKI - EVENT\" MACIEJ KUBICKI ",
    "Miejsce Realizacji Województwo": "WIELKOPOLSKIE",
    "Grantobiorca Miejscowość": "Poznań",
    "Grantobiorca Ulica": "Grunwaldzka",
    "Grantobiorca Nr budynku": "33b",
    "Grantobiorca Kod pocztowy": "60-783",
    "Wartość wsparcia": 504800.96
}