{
    "name": "\"Relax Events\" - rozszerzenie działalności o nową usługę: organizację eventów, konferencji i wydarzeń w nowoczesnej sezonowej hali namiotowej. Region 5 - woj. wielkopolskie",
    "address": "WIELKOPOLSKIE Słupia pod Bralinem 83b 63-642",
    "description": "Nazwa: JOLANTA TROSKA RELAX<br>Miejsce Realizacji Województwo: WIELKOPOLSKIE<br>Grantobiorca Miejscowość: Słupia pod Bralinem<br>Grantobiorca Ulica: <br>Grantobiorca Nr budynku: 83b<br>Grantobiorca Kod pocztowy: 63-642<br>Wartość wsparcia: 504000",
    "styleUrl": "#icon-1899-0288D1",
    "Nazwa": "JOLANTA TROSKA RELAX",
    "Miejsce Realizacji Województwo": "WIELKOPOLSKIE",
    "Grantobiorca Miejscowość": "Słupia pod Bralinem",
    "Grantobiorca Ulica": null,
    "Grantobiorca Nr budynku": "83b",
    "Grantobiorca Kod pocztowy": "63-642",
    "Wartość wsparcia": 504000.0
}