{
    "name": "Wzmocnienie przedsiębiorstwa NATALIA GIBAŁA NESS poprzez dywersyfikację,wprowadzenie nowych produktów i usług. Projekt realizowany w regionie małopolskim.",
    "address": "MAŁOPOLSKIE Kraków Nad Zalewem 15 30-235",
    "description": "Nazwa: NATALIA GIBAŁA NESS<br>Miejsce Realizacji Województwo: MAŁOPOLSKIE<br>Grantobiorca Miejscowość: Kraków<br>Grantobiorca Ulica: Nad Zalewem<br>Grantobiorca Nr budynku: 15<br>Grantobiorca Kod pocztowy: 30-235<br>Wartość wsparcia: 406767.46",
    "styleUrl": "#icon-1899-0288D1",
    "Nazwa": "NATALIA GIBAŁA NESS",
    "Miejsce Realizacji Województwo": "MAŁOPOLSKIE",
    "Grantobiorca Miejscowość": "Kraków",
    "Grantobiorca Ulica": "Nad Zalewem",
    "Grantobiorca Nr budynku": "15",
    "Grantobiorca Kod pocztowy": "30-235",
    "Wartość wsparcia": 406767.46
}