{
    "name": "Żłobek samorządowy w Tarłowie",
    "address": "Świętokrzyskie Opatowski Tarłów 27-515 Kleparz 1",
    "description": "opis: Województwo: Świętokrzyskie<br>Powiat: Opatowski<br>Miejscowość: Tarłów<br>Kod pocztowy: 27-515<br>Ulica: Kleparz<br>Numer: 1<br>adres: Świętokrzyskie Opatowski Tarłów 27-515 Kleparz 1<br>Województwo: Świętokrzyskie<br>Powiat: Opatowski<br>Miejscowość: Tarłów<br>Kod pocztowy: 27-515<br>Ulica: Kleparz<br>Numer: 1",
    "styleUrl": "#icon-1899-DB4436",
    "opis": "Województwo: Świętokrzyskie\nPowiat: Opatowski\nMiejscowość: Tarłów\nKod pocztowy: 27-515\nUlica: Kleparz\nNumer: 1",
    "adres": "Świętokrzyskie Opatowski Tarłów 27-515 Kleparz 1",
    "Województwo": "Świętokrzyskie",
    "Powiat": "Opatowski",
    "Miejscowość": "Tarłów",
    "Kod pocztowy": "27-515",
    "Ulica": "Kleparz",
    "Numer": "1"
}