[
  {
    "name": "Dywersyfikacja usług przedsiębiorstwa: ekoinnowacje w turystyce noclegowej regionu 5, województwo dolnośląskie.",
    "address": "DOLNOŚLĄSKIE Wrocław Poleska 40 51-354",
    "description": "Nazwa: MOHITO AGENCY KRZYSZTOF CHRUŚLIŃSKI <br>Miejsce Realizacji Województwo: DOLNOŚLĄSKIE<br>Grantobiorca Miejscowość: Wrocław<br>Grantobiorca Ulica: Poleska<br>Grantobiorca Nr budynku: 40<br>Grantobiorca Kod pocztowy: 51-354<br>Wartość wsparcia: 528560.48",
    "styleUrl": "#icon-1899-0288D1",
    "Nazwa": "MOHITO AGENCY KRZYSZTOF CHRUŚLIŃSKI ",
    "Miejsce Realizacji Województwo": "DOLNOŚLĄSKIE",
    "Grantobiorca Miejscowość": "Wrocław",
    "Grantobiorca Ulica": "Poleska",
    "Grantobiorca Nr budynku": "40",
    "Grantobiorca Kod pocztowy": "51-354",
    "Wartość wsparcia": 528560.48
  }
]