[
  {
    "name": "Dywersyfikacja działalności Wlazło Krzysztof Przedsiębiorstwo Handlowo-Usługowe \"ARKADIA\" Obejmująca poszerzenie bazy usługowej",
    "address": "MAZOWIECKIE Przytyk Tomaszowska 17 26-650",
    "description": "Nazwa: Wlazło Krzysztof Przedsiębiorstwo Handlowo-Usługowe \"ARKADIA\"<br>Miejsce Realizacji Województwo: MAZOWIECKIE<br>Grantobiorca Miejscowość: Przytyk<br>Grantobiorca Ulica: Tomaszowska<br>Grantobiorca Nr budynku: 17<br>Grantobiorca Kod pocztowy: 26-650<br>Wartość wsparcia: 209306.14",
    "styleUrl": "#icon-1899-0288D1",
    "Nazwa": "Wlazło Krzysztof Przedsiębiorstwo Handlowo-Usługowe \"ARKADIA\"",
    "Miejsce Realizacji Województwo": "MAZOWIECKIE",
    "Grantobiorca Miejscowość": "Przytyk",
    "Grantobiorca Ulica": "Tomaszowska",
    "Grantobiorca Nr budynku": "17",
    "Grantobiorca Kod pocztowy": "26-650",
    "Wartość wsparcia": 209306.14
  }
]