[
  {
    "name": "Dywersyfikacja działalności Hotelu Residence w Rewalu w woj. zachodniopomorskim poprzez wprowadzenie do oferty nowych usług gastronomicznych",
    "address": "ZACHODNIOPOMORSKIE Szczecin Leśna Polana 16 70-782",
    "description": "Nazwa: ŻANETA KAMIŃSKA<br>Miejsce Realizacji Województwo: ZACHODNIOPOMORSKIE<br>Grantobiorca Miejscowość: Szczecin<br>Grantobiorca Ulica: Leśna Polana<br>Grantobiorca Nr budynku: 16<br>Grantobiorca Kod pocztowy: 70-782<br>Wartość wsparcia: 539999.99",
    "styleUrl": "#icon-1899-0288D1",
    "Nazwa": "ŻANETA KAMIŃSKA",
    "Miejsce Realizacji Województwo": "ZACHODNIOPOMORSKIE",
    "Grantobiorca Miejscowość": "Szczecin",
    "Grantobiorca Ulica": "Leśna Polana",
    "Grantobiorca Nr budynku": "16",
    "Grantobiorca Kod pocztowy": "70-782",
    "Wartość wsparcia": 539999.99
  }
]