[
  {
    "name": "Druidowy Catering na Śląsku. Druid na wyciągnięcie ręki.",
    "address": "ŚLĄSKIE Ruda Śląska Chorzowska 3 41-709",
    "description": "Nazwa: ARTin spółka cywilna Krzysztof Kasprzyk, Tomasz Bartniczak, Michał Kaczmarczyk<br>Miejsce Realizacji Województwo: ŚLĄSKIE<br>Grantobiorca Miejscowość: Ruda Śląska<br>Grantobiorca Ulica: Chorzowska<br>Grantobiorca Nr budynku: 3<br>Grantobiorca Kod pocztowy: 41-709<br>Wartość wsparcia: 435915.9",
    "styleUrl": "#icon-1899-0288D1",
    "Nazwa": "ARTin spółka cywilna Krzysztof Kasprzyk, Tomasz Bartniczak, Michał Kaczmarczyk",
    "Miejsce Realizacji Województwo": "ŚLĄSKIE",
    "Grantobiorca Miejscowość": "Ruda Śląska",
    "Grantobiorca Ulica": "Chorzowska",
    "Grantobiorca Nr budynku": "3",
    "Grantobiorca Kod pocztowy": "41-709",
    "Wartość wsparcia": 435915.9
  }
]