[
  {
    "name": "Dywersyfikacja działalności w firmie Przedsiębiorstwo Transportowe \"TRANS - LIS\" Lisek Grażyna poprzez wdrożenie nowych usług (Region2)",
    "address": "MAZOWIECKIE Trablice 78 26-624",
    "description": "Nazwa: PRZEDSIĘBIORSTWO TRANSPORTOWE \" TRANS - LIS\" Lisek Grażyna<br>Miejsce Realizacji Województwo: MAZOWIECKIE<br>Grantobiorca Miejscowość: Trablice<br>Grantobiorca Ulica: <br>Grantobiorca Nr budynku: 78<br>Grantobiorca Kod pocztowy: 26-624<br>Wartość wsparcia: 538758",
    "styleUrl": "#icon-1899-0288D1",
    "Nazwa": "PRZEDSIĘBIORSTWO TRANSPORTOWE \" TRANS - LIS\" Lisek Grażyna",
    "Miejsce Realizacji Województwo": "MAZOWIECKIE",
    "Grantobiorca Miejscowość": "Trablice",
    "Grantobiorca Ulica": null,
    "Grantobiorca Nr budynku": "78",
    "Grantobiorca Kod pocztowy": "26-624",
    "Wartość wsparcia": 538758.0
  }
]