[
  {
    "name": "Mobilna gastronomia - rozwiązanie budujące odporność Gospody u Wandy i Jędrusia znajdującej się w Milówce w woj. śląskim",
    "address": "ŚLĄSKIE Milówka Graniczna 1 34-360",
    "description": "Nazwa: MATUSZEK WANDA GOSPODA U WANDZI I JĘDRUSIA<br>Miejsce Realizacji Województwo: ŚLĄSKIE<br>Grantobiorca Miejscowość: Milówka<br>Grantobiorca Ulica: Graniczna<br>Grantobiorca Nr budynku: 1<br>Grantobiorca Kod pocztowy: 34-360<br>Wartość wsparcia: 299570.31",
    "styleUrl": "#icon-1899-0288D1",
    "Nazwa": "MATUSZEK WANDA GOSPODA U WANDZI I JĘDRUSIA",
    "Miejsce Realizacji Województwo": "ŚLĄSKIE",
    "Grantobiorca Miejscowość": "Milówka",
    "Grantobiorca Ulica": "Graniczna",
    "Grantobiorca Nr budynku": "1",
    "Grantobiorca Kod pocztowy": "34-360",
    "Wartość wsparcia": 299570.31
  }
]