[
  {
    "name": "Wzmocnienie przedsiębiorstwa POLTRONA STUDIO SPÓŁKA Z OGRANICZONĄ ODPOWIEDZIALNOŚCIĄ poprzez wprowadzenie nowych produktów i usług oraz dywersyfikację działalności. Projekt realizowany w regionie zachodniopomorskim",
    "address": "ZACHODNIOPOMORSKIE Szczecin pl. Plac Stefana Batorego 4 70-207",
    "description": "Nazwa: POLTRONA STUDIO SPÓŁKA Z OGRANICZONĄ ODPOWIEDZIALNOŚCIĄ<br>Miejsce Realizacji Województwo: ZACHODNIOPOMORSKIE<br>Grantobiorca Miejscowość: Szczecin<br>Grantobiorca Ulica: pl. Plac Stefana Batorego<br>Grantobiorca Nr budynku: 4<br>Grantobiorca Kod pocztowy: 70-207<br>Wartość wsparcia: 413996.38",
    "styleUrl": "#icon-1899-0288D1",
    "Nazwa": "POLTRONA STUDIO SPÓŁKA Z OGRANICZONĄ ODPOWIEDZIALNOŚCIĄ",
    "Miejsce Realizacji Województwo": "ZACHODNIOPOMORSKIE",
    "Grantobiorca Miejscowość": "Szczecin",
    "Grantobiorca Ulica": "pl. Plac Stefana Batorego",
    "Grantobiorca Nr budynku": "4",
    "Grantobiorca Kod pocztowy": "70-207",
    "Wartość wsparcia": 413996.38
  }
]