[
  {
    "name": "Dywersyfikacja działalności spółki poprzez wprowadzenie do oferty nowych usług związanych z organizacją targów, konferencji i spotkań - odporny śląsk - region śląski. (REGION 4)",
    "address": "ŚLĄSKIE Tarnowskie Góry Gliwicka 35 42-600",
    "description": "Nazwa: DREAM EVENTS POLAND SPÓŁKA Z OGRANICZONĄ ODPOWIEDZIALNOŚCIĄ<br>Miejsce Realizacji Województwo: ŚLĄSKIE<br>Grantobiorca Miejscowość: Tarnowskie Góry<br>Grantobiorca Ulica: Gliwicka<br>Grantobiorca Nr budynku: 35<br>Grantobiorca Kod pocztowy: 42-600<br>Wartość wsparcia: 419944",
    "styleUrl": "#icon-1899-0288D1",
    "Nazwa": "DREAM EVENTS POLAND SPÓŁKA Z OGRANICZONĄ ODPOWIEDZIALNOŚCIĄ",
    "Miejsce Realizacji Województwo": "ŚLĄSKIE",
    "Grantobiorca Miejscowość": "Tarnowskie Góry",
    "Grantobiorca Ulica": "Gliwicka",
    "Grantobiorca Nr budynku": "35",
    "Grantobiorca Kod pocztowy": "42-600",
    "Wartość wsparcia": 419944.0
  }
]