[
  {
    "name": "Gminny Klub Dziecięcy \"Bajka\" z oddziałami w Zebrzydowicach, Kończycach Małych, Kaczycach",
    "address": "Śląskie Cieszyński Kończyce Małe 43-410 Jagiellońska 22A",
    "description": "opis: Województwo: Śląskie<br>Powiat: Cieszyński<br>Miejscowość: Kończyce Małe<br>Kod pocztowy: 43-410<br>Ulica: Jagiellońska<br>Numer: 22A<br>adres: Śląskie Cieszyński Kończyce Małe 43-410 Jagiellońska 22A<br>Województwo: Śląskie<br>Powiat: Cieszyński<br>Miejscowość: Kończyce Małe<br>Kod pocztowy: 43-410<br>Ulica: Jagiellońska<br>Numer: 22A",
    "styleUrl": "#icon-1899-DB4436",
    "opis": "Województwo: Śląskie\nPowiat: Cieszyński\nMiejscowość: Kończyce Małe\nKod pocztowy: 43-410\nUlica: Jagiellońska\nNumer: 22A",
    "adres": "Śląskie Cieszyński Kończyce Małe 43-410 Jagiellońska 22A",
    "Województwo": "Śląskie",
    "Powiat": "Cieszyński",
    "Miejscowość": "Kończyce Małe",
    "Kod pocztowy": "43-410",
    "Ulica": "Jagiellońska",
    "Numer": "22A"
  }
]