[
  {
    "name": "Zwiększenie odporności przedsiębiorstwa ARAVEL Katarzyna Boczek na sytuacje kryzysowe poprzez zapewnienie możliwości jego rozwoju i rozszerzenia działalności – wprowadzenie na rynek nowych usług: zajęcia jogi, wynajem rowerów tradycyjnych i elektrycznych, samodzielne zameldowanie i wymeldowanie w apartamentach (REGION 5: województwo dolnośląskie)",
    "address": "DOLNOŚLĄSKIE Wrocław Tadeusza Kościuszki 51B 50-011",
    "description": "Nazwa: ARAVEL Katarzyna Boczek <br>Miejsce Realizacji Województwo: DOLNOŚLĄSKIE<br>Grantobiorca Miejscowość: Wrocław<br>Grantobiorca Ulica: Tadeusza Kościuszki<br>Grantobiorca Nr budynku: 51B<br>Grantobiorca Kod pocztowy: 50-011<br>Wartość wsparcia: 237042.58",
    "styleUrl": "#icon-1899-0288D1",
    "Nazwa": "ARAVEL Katarzyna Boczek ",
    "Miejsce Realizacji Województwo": "DOLNOŚLĄSKIE",
    "Grantobiorca Miejscowość": "Wrocław",
    "Grantobiorca Ulica": "Tadeusza Kościuszki",
    "Grantobiorca Nr budynku": "51B",
    "Grantobiorca Kod pocztowy": "50-011",
    "Wartość wsparcia": 237042.58
  }
]