[
  {
    "name": "Budowa i wyposażenie mroźni magazynowej wraz z infrastrukturą towarzyszącą, zakup niezbędnych środków transportu wewnętrznego, sprzętu IT do zarządzania procesami logistycznymi oraz fotowoltaiki, monitoringu i alarmu Centrum Dystrybucyjnym SOT w Szczecini",
    "address": "Handlowa 4 15-399 Białystok",
    "description": "Grantobiorca nazwa: Spółdzielnia Obrotu Towarowego Przemysłu Mleczarskiego<br>Wartość grantu: 2,184,095.60 zł<br>Grantobiorca Ulica: Handlowa<br>Grantobiorca Nr budynku: 4<br>Grantobiorca Kod pocztowy: 15-399<br>Grantobiorca Miejscowość: Białystok",
    "styleUrl": "#icon-1566-7CB342",
    "Grantobiorca nazwa": "Spółdzielnia Obrotu Towarowego Przemysłu Mleczarskiego",
    "Wartość grantu": "2,184,095.60 zł",
    "Grantobiorca Ulica": "Handlowa",
    "Grantobiorca Nr budynku": "4",
    "Grantobiorca Kod pocztowy": "15-399",
    "Grantobiorca Miejscowość": "Białystok"
  }
]