[
  {
    "name": "Rozwój i dywersyfikacja działalności PHU ADEK - Adrian Ryndak w regionie śląskim poprzez uruchomienie stałej produkcji tortów, ekspansję mobilnej sprzedaży oraz wprowadzenie cateringu z dostawą do klienta",
    "address": "ŚLĄSKIE Kozy Jaworowa 3 43-340",
    "description": "Nazwa: PHU ADEK - Adrian Ryndak<br>Miejsce Realizacji Województwo: ŚLĄSKIE<br>Grantobiorca Miejscowość: Kozy<br>Grantobiorca Ulica: Jaworowa<br>Grantobiorca Nr budynku: 3<br>Grantobiorca Kod pocztowy: 43-340<br>Wartość wsparcia: 539100",
    "styleUrl": "#icon-1899-0288D1",
    "Nazwa": "PHU ADEK - Adrian Ryndak",
    "Miejsce Realizacji Województwo": "ŚLĄSKIE",
    "Grantobiorca Miejscowość": "Kozy",
    "Grantobiorca Ulica": "Jaworowa",
    "Grantobiorca Nr budynku": "3",
    "Grantobiorca Kod pocztowy": "43-340",
    "Wartość wsparcia": 539100.0
  }
]