[
  {
    "name": "Rozwój i dywersyfikacja oferty RAAD na Uroczysku Paweł Iwanicki w województwie śląskim w ramach zwiększania konkurencyjności gospodarki i wspierania mikroprzedsiębiorstw (Region 5- dolnośląskie)",
    "address": "DOLNOŚLĄSKIE Szklarska Poręba Hugona Kołłątaja 3a 58-580",
    "description": "Nazwa: RAAD na Uroczysku Paweł Iwanicki <br>Miejsce Realizacji Województwo: DOLNOŚLĄSKIE<br>Grantobiorca Miejscowość: Szklarska Poręba<br>Grantobiorca Ulica: Hugona Kołłątaja<br>Grantobiorca Nr budynku: 3a<br>Grantobiorca Kod pocztowy: 58-580<br>Wartość wsparcia: 404218.26",
    "styleUrl": "#icon-1899-0288D1",
    "Nazwa": "RAAD na Uroczysku Paweł Iwanicki ",
    "Miejsce Realizacji Województwo": "DOLNOŚLĄSKIE",
    "Grantobiorca Miejscowość": "Szklarska Poręba",
    "Grantobiorca Ulica": "Hugona Kołłątaja",
    "Grantobiorca Nr budynku": "3a",
    "Grantobiorca Kod pocztowy": "58-580",
    "Wartość wsparcia": 404218.26
  }
]