[
  {
    "name": "Rewitalizacja zabytkowego centrum Brześcia Kujawskiego",
    "description": "Nr referencyjny umowy: <br>Data zawarcia umowy pożyczki: <br>Kwota pożyczki: <br>Nazwa pożyczkobiorcy: <br>Lokalizacja: 52.60383528234406, 18.901028184129277<br>1 Lokalizacja/Miasto Inwestycji: Brześć Kujawski<br>Opis projektu: Rewitalizacja zabytkowego centrum Brześcia Kujawskiego, w ramach której planowane jest wykonanie zagospodarowania zaniedbanych terenów:<br>- Placu Władysława Łokietka w Brześciu Kujawskim, w tym uporządkowanie zieleni, przebudowa i remont placu głównego, miejsc postojowych, budowę fontanny, obiektów małej architektury wraz z niezbędnymi urządzeniami i infrastrukturą techniczną.",
    "styleUrl": "#icon-1886-7CB342",
    "Nr referencyjny umowy": null,
    "Data zawarcia umowy pożyczki": null,
    "Kwota pożyczki": null,
    "Nazwa pożyczkobiorcy": null,
    "Lokalizacja": "52.60383528234406, 18.901028184129277",
    "1 Lokalizacja/Miasto Inwestycji": "Brześć Kujawski",
    "Opis projektu": "Rewitalizacja zabytkowego centrum Brześcia Kujawskiego, w ramach której planowane jest wykonanie zagospodarowania zaniedbanych terenów:\n- Placu Władysława Łokietka w Brześciu Kujawskim, w tym uporządkowanie zieleni, przebudowa i remont placu głównego, miejsc postojowych, budowę fontanny, obiektów małej architektury wraz z niezbędnymi urządzeniami i infrastrukturą techniczną."
  }
]