{
    "name": "Dywersyfikacja działalności gastronomicznej i rekreacyjnej Firmy Handlowej Woj- ciech Dobrzelecki poprzez budowę domków wypoczynkowych, utworzenie strefy SPA oraz cyfryzację usług w Regionie Kujawsko-Pomorskim.",
    "address": "KUJAWSKO-POMORSKIE Ciechocinek Zdrojowa 18a 87-720",
    "description": "Nazwa: FIRMA HANDLOWA WOJCIECH DOBRZELECKI<br>Miejsce Realizacji Województwo: KUJAWSKO-POMORSKIE<br>Grantobiorca Miejscowość: Ciechocinek<br>Grantobiorca Ulica: Zdrojowa<br>Grantobiorca Nr budynku: 18a<br>Grantobiorca Kod pocztowy: 87-720<br>Wartość wsparcia: 501376.03",
    "styleUrl": "#icon-1899-0288D1",
    "Nazwa": "FIRMA HANDLOWA WOJCIECH DOBRZELECKI",
    "Miejsce Realizacji Województwo": "KUJAWSKO-POMORSKIE",
    "Grantobiorca Miejscowość": "Ciechocinek",
    "Grantobiorca Ulica": "Zdrojowa",
    "Grantobiorca Nr budynku": "18a",
    "Grantobiorca Kod pocztowy": "87-720",
    "Wartość wsparcia": 501376.03
}